qcam/__init__.py
qcam/image2ascii.py
qcam/qCam.py
qcam_sdk-0.0.5.dist-info/LICENSE
qcam_sdk-0.0.5.dist-info/METADATA
qcam_sdk-0.0.5.dist-info/WHEEL
qcam_sdk-0.0.5.dist-info/top_level.txt
qcam_sdk-0.0.5.dist-info/RECORD
